scitq/__init__.py
scitq/client.py
scitq/client_events.py
scitq/constants.py
scitq/debug.py
scitq/default_settings.py
scitq/fetch.py
scitq/launch.py
scitq/lib.py
scitq/manage.py
scitq/path.py
scitq/remote.py
scitq/util.py
scitq/workflow.py
scitq/ansible/.DS_Store
scitq/ansible/README.md
scitq/ansible/.vscode/settings.json
scitq/ansible/etc/ansible.cfg
scitq/ansible/playbooks/add_docker.j2
scitq/ansible/playbooks/add_docker.yaml
scitq/ansible/playbooks/add_docker2.j2
scitq/ansible/playbooks/add_drivers.yaml
scitq/ansible/playbooks/add_in_firewall.yaml
scitq/ansible/playbooks/add_in_nfs_exports.j2
scitq/ansible/playbooks/add_in_nfs_exports.yaml
scitq/ansible/playbooks/add_in_nfs_exports2.j2
scitq/ansible/playbooks/add_nfs.yaml
scitq/ansible/playbooks/add_rclone.yaml
scitq/ansible/playbooks/add_s3authentication.yaml
scitq/ansible/playbooks/add_s3authentication_config.j2
scitq/ansible/playbooks/add_s3authentication_credentials.j2
scitq/ansible/playbooks/add_scitq.j2
scitq/ansible/playbooks/add_scitq.yaml
scitq/ansible/playbooks/add_scratch.yaml
scitq/ansible/playbooks/add_swap.yaml
scitq/ansible/playbooks/check_after_reboot.yaml
scitq/ansible/playbooks/deploy_one_vm.yaml
scitq/ansible/playbooks/deploy_one_vm_manual.yaml
scitq/ansible/playbooks/deploy_vm_azure.yaml
scitq/ansible/playbooks/deploy_vm_ovh.yaml
scitq/ansible/playbooks/destroy_vm.yaml
scitq/ansible/playbooks/destroy_vm_azure.yaml
scitq/ansible/playbooks/destroy_vm_manual.yaml
scitq/ansible/playbooks/destroy_vm_ovh.yaml
scitq/ansible/playbooks/remove_from_etchosts.yaml
scitq/ansible/playbooks/remove_from_firewall.yaml
scitq/ansible/playbooks/remove_from_nfs_exports.yaml
scitq/ansible/playbooks/remove_from_static_inventory.yaml
scitq/ansible/playbooks/update_workers.yaml
scitq/ansible/scitq/01-scitq-default
scitq/ansible/scitq/__pycache__/sqlite_inventory.cpython-310.pyc
scitq/ansible/scitq/__pycache__/sqlite_inventory.cpython-312.pyc
scitq/ansible/scitq/__pycache__/sqlite_inventory.cpython-38.pyc
scitq-1.3.8.dist-info/licenses/LICENSE
scitq-1.3.8.dist-info/METADATA
scitq-1.3.8.dist-info/WHEEL
scitq-1.3.8.dist-info/entry_points.txt
scitq-1.3.8.dist-info/top_level.txt
scitq-1.3.8.dist-info/RECORD
