Metadata-Version: 2.4
Name: scitq
Version: 1.3.8
Summary: A (distributed) scientific task queue
Author: Raynald de Lahondès, Rémi Tan
Project-URL: Homepage, https://github.com/gmtsciencedev/scitq
Project-URL: Bug Tracker, https://github.com/gmtsciencedev/scitq/issues
Project-URL: Documentation, https://scitq.readthedocs.io/
Classifier: Programming Language :: Python :: 3
Classifier: License :: OSI Approved :: MIT License
Classifier: Development Status :: 5 - Production/Stable
Classifier: Operating System :: OS Independent
Requires-Python: >=3.8
License-File: LICENSE
Requires-Dist: Flask<2.2
Requires-Dist: flask-sqlalchemy<3.0.0
Requires-Dist: sqlalchemy<2
Requires-Dist: Flask-Migrate
Requires-Dist: flask-restx==1.2.0
Requires-Dist: flask-socketio>=5.2.0
Requires-Dist: requests
Requires-Dist: psutil
Requires-Dist: tabulate
Requires-Dist: psycopg2-binary
Requires-Dist: python-dotenv
Requires-Dist: urwid
Requires-Dist: filelock
Requires-Dist: azure-mgmt-subscription
Requires-Dist: azure-mgmt-resourcegraph
Requires-Dist: azure-identity
Requires-Dist: azure-mgmt-compute
Requires-Dist: azure-core>=1.28
Requires-Dist: azure-keyvault
Requires-Dist: azure-cli
Requires-Dist: azure-storage-blob>=12
Requires-Dist: pandas<2.2
Requires-Dist: ovh
Requires-Dist: lxml
Requires-Dist: rclone_python==0.1.21
Dynamic: license-file
